matrix_io.py
matrix_io-0.0.2.dist-info/DESCRIPTION.rst
matrix_io-0.0.2.dist-info/METADATA
matrix_io-0.0.2.dist-info/RECORD
matrix_io-0.0.2.dist-info/WHEEL
matrix_io-0.0.2.dist-info/metadata.json
matrix_io-0.0.2.dist-info/top_level.txt
