Metadata-Version: 2.0
Name: matrix-io
Version: 0.0.2
Summary: I/O for stramable sparse matrices.
Home-page: https://github.com/JosuaKrause/matrix_io
Author: Josua Krause
Author-email: josua.krause@gmail.com
License: MIT
Keywords: sparse matrix io stream
Platform: UNKNOWN
Classifier: Development Status :: 4 - Beta
Classifier: License :: OSI Approved :: MIT License
Classifier: Programming Language :: Python :: 2
Classifier: Programming Language :: Python :: 2.6
Classifier: Programming Language :: Python :: 2.7
Classifier: Programming Language :: Python :: 3
